pomidor/__init__.py
pomidor/actions.py
pomidor/pomidor_runner.py
tests/__init__.py
tests/negative_pomidor_tests.py
tests/negative_pomidory/__init__.py
tests/pageObjects/__init__.py
tests/pageObjects/page_factory.py
pomidor-0.0.2.dist-info/LICENSE
pomidor-0.0.2.dist-info/METADATA
pomidor-0.0.2.dist-info/WHEEL
pomidor-0.0.2.dist-info/top_level.txt
pomidor-0.0.2.dist-info/RECORD
