Metadata-Version: 2.1
Name: pomidor
Version: 0.0.2
Summary: A BDD-style Selenium-driven browser automation in Python
Home-page: https://github.com/symon-storozhenko/pomidor
Author: Symon Storozhenko
Author-email: symon.storozhenko@gmail.com
License: UNKNOWN
Platform: UNKNOWN
Classifier: Programming Language :: Python :: 3
Classifier: License :: OSI Approved :: Apache Software License
Classifier: Operating System :: OS Independent
Requires-Python: >=3.6
Requires-Dist: selenium
Requires-Dist: pytest
